[{"name":"Univers parallèle III à Tulle du 18 janvier au 28 février 2020","date_start":"2020-01-18","date_end":"2020-02-28","address":" La Cour Des Arts (2 Rue Des Portes Chanac), 19","category":"Expositions","sub_category":" La Cour Des Arts (2 Rue Des Portes Chanac)","photo_url":"https://agendaculturel.emstorage.fr/crop400x266/exposition-univers-parallele-iii-janvier-20191210163003.jpg","lat":45.268483700000004,"long":1.7662868596404582,"description":"","event_url":"no_url"},{"name":"Melting Drops #4 à Tulle le 22 février 2020","date_start":"2020-02-22","date_end":"2020-02-22","address":" Des lendemains qui chantent  , 19","category":"Concerts","sub_category":" Des lendemains qui chantent  ","photo_url":"https://static.agendaculturel.fr/e/400x266/2012/09/04/default-concert.jpg","lat":45.279398,"long":1.7849121,"description":"  Quasiment un an jour pour jour après l'édition #3, Melting Drops revient à Des Lendemains Qui Chantent pour une nouvelle édition At Home. Des artistes éclectiques (des locaux accompagnés de guests de qualité) composent l'affiche de cette longue soirée. La scénographie sera aussi revisité pour vivre une expérience sonore et visuelle qui sort des sentiers battus.  Cette édition sera musicalement axée sur la house et la techouse groovy pour l'entame et sur de la techno et de l'acid en conclusion.  Avec entre autres Crâne de poule, Midilink et Kzr Totem. ","event_url":"no_url"}]