[{"name":"Wally : Le Projet Derli à Millau le 1er février 2020","date_start":"2020-02-01","date_end":"2020-02-01","address":" Maison du peuple Millau  , 12","category":"Concerts","sub_category":" Maison du peuple Millau  ","photo_url":"https://agendaculturel.emstorage.fr/crop400x266/wally-le-projet-derli-TMASTER_rZ7SnyZ1AdZYbp-h0-27342337.jpg","lat":44.0974238,"long":3.0815640359055747,"description":"LE PROJET DERLI // WallyProjet Newton chante en français ! en after Le Projet DerliCe n'est pas faire offense à Wally que de parler de la longévité de son parcours artistique, lui qui a fêté récemment ses 50 ans par une tournée anniversaire.Avec Le Projet Derli, plus de filtre pour détourner l'émotion, plus de kazoo, mais un orchestre, plus de non-sens, mais des chansons intimes comme des instantanés de sa vie. Réservez vos places de concert pour : WALLY : LE PROJET DERLI - THEATRE LA MAISON DU PEUPLE Le prix des places est : 11.50 €Date : samedi 1 février 2020 Vous disposez par ailleurs du service e-ticket pour imprimer vos billets à domicile dès la fin de commande pour WALLY : LE PROJET DERLI ainsi que du plan de salle interactif pour choisir vos places dans le lieu : THEATRE LA MAISON DU PEUPLE. ","event_url":"no_url"}]